Lagranto-0.3.1.data/scripts/quickview.py
lagranto/__init__.py
lagranto/formats.py
lagranto/lagranto.py
lagranto/plotting.py
lagranto/tools.py
Lagranto-0.3.1.dist-info/AUTHORS.txt
Lagranto-0.3.1.dist-info/LICENSE.txt
Lagranto-0.3.1.dist-info/METADATA
Lagranto-0.3.1.dist-info/WHEEL
Lagranto-0.3.1.dist-info/top_level.txt
Lagranto-0.3.1.dist-info/RECORD
