Metadata-Version: 2.1
Name: Lagranto
Version: 0.3.1
Summary: Library to work with trajectories.
Home-page: https://lagranto.readthedocs.io/en/latest/
Download-URL: https://git.iac.ethz.ch/npiaget/Lagranto
Author: Nicolas Piaget
Author-email: nicolas.piaget@env.ethz.ch
Maintainer: Nicolas Piaget
Maintainer-email: nicolas.piaget@env.ethz.ch
License: GPL-3.0+
Keywords: data,science,meteorology,climate trajectories
Platform: UNKNOWN
Classifier: Development Status :: 4 - Beta
Classifier: Intended Audience :: Science/Research
Classifier: License :: OSI Approved :: GNU General Public License v3 or later (GPLv3+)
Classifier: Programming Language :: Python :: 3
Classifier: Programming Language :: Python :: 3.7
Classifier: Programming Language :: Python :: 3.8
Classifier: Programming Language :: Python :: 3.9
Classifier: Programming Language :: Python :: 3.10
Classifier: Topic :: Scientific/Engineering :: Atmospheric Science
Requires-Python: >=3.7
License-File: LICENSE.txt
License-File: AUTHORS.txt
Requires-Dist: path.py
Requires-Dist: cartopy
Requires-Dist: numpy
Requires-Dist: netCDF4
Requires-Dist: matplotlib
Provides-Extra: docs
Requires-Dist: Sphinx ; extra == 'docs'
Provides-Extra: testing
Requires-Dist: pytest ; extra == 'testing'
